{"teams":["三个臭皮匠","试者如斯夫，不舍昼夜","好好想想队","堂吉诃德","如果爆零能报销回家车费吗","彰显王威吧，踏遍世间的十二辉剑！","歪日，这么虾头？","华为手机","网瘾犯了求求你把牌子给我","帮帮我，评测机老爷爷！","金牌厨师","对了没？如队","嘉然今天吃汉堡","DP_PTSD","遥遥领先于友队","我太想AC了","4000g_Pt","我宣布以上成绩无效","吃堡没吃饱","啊对对队"],"conts":["vj6","vj8","vj9"],"data":[{"name":"三个臭皮匠","type":"line","data":[100,88.71,85.03],"markLine":{"data":[{"type":"average","name":"平均值"}]}},{"name":"试者如斯夫，不舍昼夜","type":"line","data":[83.17,65.73,55.77],"markLine":{"data":[{"type":"average","name":"平均值"}]}},{"name":"好好想想队","type":"line","data":[83,100,100],"markLine":{"data":[{"type":"average","name":"平均值"}]}},{"name":"堂吉诃德","type":"line","data":[82.83,65.6,70.57],"markLine":{"data":[{"type":"average","name":"平均值"}]}},{"name":"如果爆零能报销回家车费吗","type":"line","data":[82.67,76.84,85.2],"markLine":{"data":[{"type":"average","name":"平均值"}]}},{"name":"彰显王威吧，踏遍世间的十二辉剑！","type":"line","data":[66,77.31,56],"markLine":{"data":[{"type":"average","name":"平均值"}]}},{"name":"歪日，这么虾头？","type":"line","data":[65.87,77.15,56.11],"markLine":{"data":[{"type":"average","name":"平均值"}]}},{"name":"华为手机","type":"line","data":[65.73,53.77,85.37],"markLine":{"data":[{"type":"average","name":"平均值"}]}},{"name":"网瘾犯了求求你把牌子给我","type":"line","data":[65.6,88.53,84.86],"markLine":{"data":[{"type":"average","name":"平均值"}]}},{"name":"帮帮我，评测机老爷爷！","type":"line","data":[65.46,65.2,70.28],"markLine":{"data":[{"type":"average","name":"平均值"}]}},{"name":"金牌厨师","type":"line","data":[65.33,65.46,55.88],"markLine":{"data":[{"type":"average","name":"平均值"}]}},{"name":"对了没？如队","type":"line","data":[65.2,54.22,55.43],"markLine":{"data":[{"type":"average","name":"平均值"}]}},{"name":"嘉然今天吃汉堡","type":"line","data":[65.06,54,0],"markLine":{"data":[{"type":"average","name":"平均值"}]}},{"name":"DP_PTSD","type":"line","data":[64.93,65.33,55.65],"markLine":{"data":[{"type":"average","name":"平均值"}]}},{"name":"遥遥领先于友队","type":"line","data":[64.8,77,70.43],"markLine":{"data":[{"type":"average","name":"平均值"}]}},{"name":"我太想AC了","type":"line","data":[48.5,42.93,41.4],"markLine":{"data":[{"type":"average","name":"平均值"}]}},{"name":"4000g_Pt","type":"line","data":[48.4,54.11,55.54],"markLine":{"data":[{"type":"average","name":"平均值"}]}},{"name":"我宣布以上成绩无效","type":"line","data":[48.3,42.84,41.48],"markLine":{"data":[{"type":"average","name":"平均值"}]}},{"name":"吃堡没吃饱","type":"line","data":[48.2,53.89,99.8],"markLine":{"data":[{"type":"average","name":"平均值"}]}},{"name":"啊对对队","type":"line","data":[32.06,32.06,27.54],"markLine":{"data":[{"type":"average","name":"平均值"}]}}],"scores":{"三个臭皮匠":[100,88.71,85.03],"试者如斯夫，不舍昼夜":[83.17,65.73,55.77],"好好想想队":[83,100,100],"堂吉诃德":[82.83,65.6,70.57],"如果爆零能报销回家车费吗":[82.67,76.84,85.2],"彰显王威吧，踏遍世间的十二辉剑！":[66,77.31,56],"歪日，这么虾头？":[65.87,77.15,56.11],"华为手机":[65.73,53.77,85.37],"网瘾犯了求求你把牌子给我":[65.6,88.53,84.86],"帮帮我，评测机老爷爷！":[65.46,65.2,70.28],"金牌厨师":[65.33,65.46,55.88],"对了没？如队":[65.2,54.22,55.43],"嘉然今天吃汉堡":[65.06,54,0],"DP_PTSD":[64.93,65.33,55.65],"遥遥领先于友队":[64.8,77,70.43],"我太想AC了":[48.5,42.93,41.4],"4000g_Pt":[48.4,54.11,55.54],"我宣布以上成绩无效":[48.3,42.84,41.48],"吃堡没吃饱":[48.2,53.89,99.8],"啊对对队":[32.06,32.06,27.54]},"teamStats":{"vj6":{"三个臭皮匠":"1/6/100.00","试者如斯夫，不舍昼夜":"2/5/83.17","好好想想队":"3/5/83.00","堂吉诃德":"4/5/82.83","如果爆零能报销回家车费吗":"5/5/82.67","彰显王威吧，踏遍世间的十二辉剑！":"6/4/66.00","歪日，这么虾头？":"7/4/65.87","华为手机":"8/4/65.73","网瘾犯了求求你把牌子给我":"9/4/65.60","帮帮我，评测机老爷爷！":"10/4/65.46","金牌厨师":"11/4/65.33","对了没？如队":"12/4/65.20","嘉然今天吃汉堡":"13/4/65.06","DP_PTSD":"14/4/64.93","遥遥领先于友队":"15/4/64.80","我太想AC了":"16/3/48.50","4000g_Pt":"17/3/48.40","我宣布以上成绩无效":"18/3/48.30","吃堡没吃饱":"19/3/48.20","啊对对队":"20/2/32.06"},"vj8":{"好好想想队":"1/9/100.00","三个臭皮匠":"2/8/88.71","网瘾犯了求求你把牌子给我":"3/8/88.53","彰显王威吧，踏遍世间的十二辉剑！":"4/7/77.31","歪日，这么虾头？":"5/7/77.15","遥遥领先于友队":"6/7/77.00","如果爆零能报销回家车费吗":"7/7/76.84","试者如斯夫，不舍昼夜":"8/6/65.73","堂吉诃德":"9/6/65.60","金牌厨师":"10/6/65.46","DP_PTSD":"11/6/65.33","帮帮我，评测机老爷爷！":"12/6/65.20","对了没？如队":"13/5/54.22","4000g_Pt":"14/5/54.11","嘉然今天吃汉堡":"15/5/54.00","吃堡没吃饱":"16/5/53.89","华为手机":"17/5/53.77","我太想AC了":"18/4/42.93","我宣布以上成绩无效":"19/4/42.84","啊对对队":"20/3/32.06"},"vj9":{"好好想想队":"1/7/100.00","吃堡没吃饱":"2/7/99.80","华为手机":"3/6/85.37","如果爆零能报销回家车费吗":"4/6/85.20","三个臭皮匠":"5/6/85.03","网瘾犯了求求你把牌子给我":"6/6/84.86","堂吉诃德":"7/5/70.57","遥遥领先于友队":"8/5/70.43","帮帮我，评测机老爷爷！":"9/5/70.28","歪日，这么虾头？":"10/4/56.11","彰显王威吧，踏遍世间的十二辉剑！":"11/4/56.00","金牌厨师":"12/4/55.88","试者如斯夫，不舍昼夜":"13/4/55.77","DP_PTSD":"14/4/55.65","4000g_Pt":"15/4/55.54","对了没？如队":"16/4/55.43","我宣布以上成绩无效":"17/3/41.48","我太想AC了":"18/3/41.40","啊对对队":"19/2/27.54"}}}